chatchat/__init__.py
chatchat/__main__.py
chatchat/alibaba.py
chatchat/baidu.py
chatchat/base.py
chatchat/deepseek.py
chatchat/google.py
chatchat/tencent.py
chatchat/version.py
chatchat/xunfei.py
chatchat/zhipu.py
chatchat/cli/__init__.py
chatchat/cli/chat.py
chatchat/cli/config.py
chatchat-0.3.1.dist-info/METADATA
chatchat-0.3.1.dist-info/WHEEL
chatchat-0.3.1.dist-info/entry_points.txt
chatchat-0.3.1.dist-info/licenses/LICENSE
chatchat-0.3.1.dist-info/RECORD
