Metadata-Version: 2.4
Name: chatchat
Version: 0.3.1
Summary: Large Language Models Python API
Project-URL: Homepage, https://github.com/jiauzhang/chatchat
Author-email: Jiau Zhang <jiauzhang@163.com>
License:                     GNU GENERAL PUBLIC LICENSE
License-File: LICENSE
Keywords: Artificial Intelligence
Classifier: Topic :: Scientific/Engineering :: Artificial Intelligence
Requires-Python: >=3.10
Requires-Dist: conippets>=0.1.8
Requires-Dist: httpx
